README.rst
setup.py
messengerbot/__init__.py
messengerbot/attachments.py
messengerbot/elements.py
messengerbot/messages.py
messengerbot/templates.py
messengerbot.egg-info/PKG-INFO
messengerbot.egg-info/SOURCES.txt
messengerbot.egg-info/dependency_links.txt
messengerbot.egg-info/requires.txt
messengerbot.egg-info/top_level.txt