Metadata-Version: 1.0
Name: messengerbot
Version: 0.1.1
Summary: Python client for FB Messenger Platform Bot
Home-page: https://github.com/geeknam
Author: Nam Ngo
Author-email: namngology@gmail.com
License: The MIT License (MIT)
Keywords: bot facebook messenger platform
Platform: UNKNOWN
